{
    "software": [
        {
            "name": "Visual Studio Code",
            "category": "Code Editor",
            "tasks": ["Code Writing", "Web Development", "Version Control", "Database Management"],
            "domains": ["Software Developer", "Web Developer", "Data Scientist", "Technical Writer", "Database Administrator"],
            "license": "MIT",
            "commercialUse": true,
            "description": "Visual Studio Code is a lightweight, extensible source-code editor with debugging, Git integration, and a vast ecosystem of extensions, ideal for coding across multiple languages and platforms.",
            "link": "https://code.visualstudio.com",
            "install": "sudo snap install code --classic",
            "logo": "https://code.visualstudio.com/assets/images/code-stable.png"
        },
        {
            "name": "Atom",
            "category": "Text Editor",
            "tasks": ["Code Writing", "Web Development", "Version Control"],
            "domains": ["Software Developer", "Web Developer", "Technical Writer"],
            "license": "MIT",
            "commercialUse": true,
            "description": "Atom is a hackable text editor built on Electron, with support for Git and extensive customization via packages, popular among developers.",
            "link": "https://atom.io",
            "install": "sudo snap install atom --classic",
            "logo": "https://atom.io/favicon.ico"
        },
        {
            "name": "Sublime Text",
            "category": "Text Editor",
            "tasks": ["Code Writing", "Web Development"],
            "domains": ["Software Developer", "Web Developer", "Technical Writer"],
            "license": "Proprietary (Free Evaluation)",
            "commercialUse": true,
            "description": "Sublime Text is a fast, lightweight text editor with powerful features like multiple cursors and a vast plugin ecosystem, widely used by developers.",
            "link": "https://www.sublimetext.com",
            "install": "sudo snap install sublime-text --classic",
            "logo": "https://www.sublimetext.com/images/icon.png"
        },
        {
            "name": "Vim",
            "category": "Text Editor",
            "tasks": ["Code Writing", "Web Development"],
            "domains": ["Software Developer", "System Administrator", "Web Developer"],
            "license": "Vim License",
            "commercialUse": true,
            "description": "Vim is a highly configurable, efficient text editor with a steep learning curve, beloved by power users and system administrators.",
            "link": "https://www.vim.org",
            "install": "sudo apt install vim",
            "logo": "https://www.vim.org/images/vimlogo.gif"
        },
        {
            "name": "Emacs",
            "category": "Text Editor",
            "tasks": ["Code Writing", "Web Development", "Document Editing"],
            "domains": ["Software Developer", "Technical Writer", "System Administrator"],
            "license": "GPL-3.0",
            "commercialUse": true,
            "description": "Emacs is a customizable, extensible text editor with a built-in programming language (Emacs Lisp), used for coding, writing, and more.",
            "link": "https://www.gnu.org/software/emacs/",
            "install": "sudo apt install emacs",
            "logo": "https://www.gnu.org/software/emacs/images/emacs.png"
        },
        {
            "name": "Eclipse",
            "category": "IDE",
            "tasks": ["Code Writing", "Web Development", "Database Management"],
            "domains": ["Software Developer", "Web Developer", "Engineer"],
            "license": "EPL-2.0",
            "commercialUse": true,
            "description": "Eclipse is a robust IDE primarily for Java, with extensive plugin support for C++, Python, and other languages, widely used in enterprise development.",
            "link": "https://www.eclipse.org",
            "install": "sudo apt install eclipse",
            "logo": "https://www.eclipse.org/eclipse.org-common/themes/solstice/public/images/logo/eclipse-foundation-logo.svg"
        },
        {
            "name": "NetBeans",
            "category": "IDE",
            "tasks": ["Code Writing", "Web Development"],
            "domains": ["Software Developer", "Web Developer"],
            "license": "Apache-2.0",
            "commercialUse": true,
            "description": "NetBeans is an IDE for Java development, with support for PHP, HTML5, and other languages, known for its ease of use and built-in tools.",
            "link": "https://netbeans.apache.org",
            "install": "sudo apt install netbeans",
            "logo": "https://netbeans.apache.org/images/netbeans-logo.png"
        },
        {
            "name": "IntelliJ IDEA Community Edition",
            "category": "IDE",
            "tasks": ["Code Writing", "Web Development"],
            "domains": ["Software Developer", "Web Developer"],
            "license": "Apache-2.0",
            "commercialUse": true,
            "description": "IntelliJ IDEA Community Edition is a powerful Java IDE with intelligent code assistance, also supporting other languages via plugins.",
            "link": "https://www.jetbrains.com/idea/",
            "install": "sudo snap install intellij-idea-community --classic",
            "logo": "https://www.jetbrains.com/idea/img/idea_logo.svg"
        },
        {
            "name": "PyCharm Community Edition",
            "category": "IDE",
            "tasks": ["Code Writing", "Web Development", "Data Analysis"],
            "domains": ["Software Developer", "Data Scientist", "Web Developer"],
            "license": "Apache-2.0",
            "commercialUse": true,
            "description": "PyCharm Community Edition is a Python-specific IDE with features for debugging, testing, and data science, built by JetBrains.",
            "link": "https://www.jetbrains.com/pycharm/",
            "install": "sudo snap install pycharm-community --classic",
            "logo": "https://www.jetbrains.com/pycharm/img/pycharm_logo.svg"
        },
        {
            "name": "Xcode",
            "category": "IDE",
            "tasks": ["Code Writing", "Web Development"],
            "domains": ["Software Developer", "Web Developer"],
            "license": "Apple License (Open-Source Components)",
            "commercialUse": true,
            "description": "Xcode is Apple's IDE for macOS and iOS development, with open-source components like Swift, used for app development.",
            "link": "https://developer.apple.com/xcode/",
            "install": "Available via Mac App Store",
            "logo": "https://developer.apple.com/assets/elements/icons/xcode/xcode-96x96_2x.png"
        },
        {
            "name": "Brackets",
            "category": "Code Editor",
            "tasks": ["Code Writing", "Web Development"],
            "domains": ["Web Developer", "Software Developer"],
            "license": "MIT",
            "commercialUse": true,
            "description": "Brackets is a lightweight editor focused on web development, with live preview and inline editing features.",
            "link": "http://brackets.io",
            "install": "sudo snap install brackets --classic",
            "logo": "http://brackets.io/images/brackets_icon.svg"
        },
        {
            "name": "Qt Creator",
            "category": "IDE",
            "tasks": ["Code Writing", "Circuit Design"],
            "domains": ["Software Developer", "Engineer", "Robotics Engineer"],
            "license": "GPL-3.0",
            "commercialUse": true,
            "description": "Qt Creator is an IDE for developing cross-platform applications in C++, with tools for GUI design and debugging.",
            "link": "https://www.qt.io",
            "install": "sudo apt install qtcreator",
            "logo": "https://www.qt.io/hubfs/Qt%20Logo%202021%20-%20Color%20-%20White%20Text.svg"
        },
        {
            "name": "Light Table",
            "category": "IDE",
            "tasks": ["Code Writing"],
            "domains": ["Software Developer"],
            "license": "MIT",
            "commercialUse": true,
            "description": "Light Table is an interactive IDE with real-time feedback, designed for a streamlined coding experience.",
            "link": "http://lighttable.com",
            "install": "Download from website",
            "logo": "http://lighttable.com/images/lt-icon.png"
        },
        {
            "name": "Code::Blocks",
            "category": "IDE",
            "tasks": ["Code Writing"],
            "domains": ["Software Developer", "Engineer"],
            "license": "GPL-3.0",
            "commercialUse": true,
            "description": "Code::Blocks is a lightweight IDE for C and C++, with support for multiple compilers and a plugin system.",
            "link": "http://www.codeblocks.org",
            "install": "sudo apt install codeblocks",
            "logo": "http://www.codeblocks.org/images/logo.png"
        },
        {
            "name": "Geany",
            "category": "IDE",
            "tasks": ["Code Writing"],
            "domains": ["Software Developer", "Web Developer"],
            "license": "GPL-2.0",
            "commercialUse": true,
            "description": "Geany is a lightweight IDE supporting multiple languages, with a focus on speed and simplicity.",
            "link": "https://www.geany.org",
            "install": "sudo apt install geany",
            "logo": "https://www.geany.org/static/img/geany.png"
        },
        {
            "name": "Gedit",
            "category": "Text Editor",
            "tasks": ["Code Writing", "Document Editing"],
            "domains": ["Software Developer", "Technical Writer"],
            "license": "GPL-2.0",
            "commercialUse": true,
            "description": "Gedit is a simple, general-purpose text editor from GNOME, with syntax highlighting for coding and writing.",
            "link": "https://wiki.gnome.org/Apps/Gedit",
            "install": "sudo apt install gedit",
            "logo": "https://wiki.gnome.org/Apps/Gedit?action=AttachFile&do=get&target=gedit-icon.png"
        },
        {
            "name": "Sublime Merge",
            "category": "Git Client",
            "tasks": ["Version Control"],
            "domains": ["Software Developer", "Web Developer"],
            "license": "Proprietary (Free Evaluation)",
            "commercialUse": true,
            "description": "Sublime Merge is a Git client with a sleek interface, built by the Sublime Text team for efficient version control.",
            "link": "https://www.sublimemerge.com",
            "install": "sudo snap install sublime-merge --classic",
            "logo": "https://www.sublimemerge.com/images/icon.png"
        },
        {
            "name": "GitKraken",
            "category": "Git Client",
            "tasks": ["Version Control"],
            "domains": ["Software Developer", "Web Developer"],
            "license": "Proprietary (Free Tier)",
            "commercialUse": true,
            "description": "GitKraken is a cross-platform Git client with a visual interface for managing repositories and workflows.",
            "link": "https://www.gitkraken.com",
            "install": "sudo snap install gitkraken --classic",
            "logo": "https://www.gitkraken.com/wp-content/uploads/2018/10/gitkraken-logo-dark-square.png"
        },
        {
            "name": "Penpot",
            "category": "Design Tool",
            "tasks": ["Vectorize", "Create SVGs", "Desktop Publishing"],
            "domains": ["Graphic Designer", "UX Designer", "Web Developer"],
            "license": "MPL-2.0",
            "commercialUse": true,
            "description": "Penpot is an open-source alternative to Figma, designed for collaborative UI/UX design with vector graphics support.",
            "link": "https://penpot.app",
            "install": "sudo snap install penpot",
            "logo": "https://penpot.app/images/penpot-logo-full.svg"
        },
        {
            "name": "Jupyter Notebook",
            "category": "Interactive Coding",
            "tasks": ["Code Writing", "Data Analysis", "Statistical Modeling"],
            "domains": ["Data Scientist", "Research Scientist", "Software Developer"],
            "license": "BSD-3-Clause",
            "commercialUse": true,
            "description": "Jupyter Notebook is an interactive web-based platform for running Python code, visualizing data, and creating shareable notebooks.",
            "link": "https://jupyter.org",
            "install": "pip install jupyter",
            "logo": "https://jupyter.org/assets/main-logo.svg"
        },
        {
            "name": "MySQL",
            "category": "Database",
            "tasks": ["Database Management", "Web Development", "Data Analysis"],
            "domains": ["Database Administrator", "Web Developer", "Data Analyst", "Software Developer"],
            "license": "GPL-2.0",
            "commercialUse": true,
            "description": "MySQL is a widely-used open-source relational database management system, known for its performance and reliability in web applications.",
            "link": "https://www.mysql.com",
            "install": "sudo apt install mysql-server",
            "logo": "https://www.mysql.com/common/logos/logo-mysql-170x115.png"
        },
        {
            "name": "PostgreSQL",
            "category": "Database",
            "tasks": ["Database Management", "Data Analysis", "Web Development"],
            "domains": ["Database Administrator", "Data Analyst", "Software Developer", "Web Developer"],
            "license": "PostgreSQL License",
            "commercialUse": true,
            "description": "PostgreSQL is an advanced relational database system with support for complex queries and extensibility, popular in data-heavy applications.",
            "link": "https://www.postgresql.org",
            "install": "sudo apt install postgresql",
            "logo": "https://www.postgresql.org/media/img/about/press/elephant.png"
        },
        {
            "name": "MariaDB",
            "category": "Database",
            "tasks": ["Database Management", "Web Development"],
            "domains": ["Database Administrator", "Web Developer", "Software Developer"],
            "license": "GPL-2.0",
            "commercialUse": true,
            "description": "MariaDB is a community-driven fork of MySQL, offering enhanced performance and compatibility with MySQL applications.",
            "link": "https://mariadb.org",
            "install": "sudo apt install mariadb-server",
            "logo": "https://mariadb.org/wp-content/uploads/2019/03/mariadb-logo_vertical_blue.png"
        },
        {
            "name": "SQLite",
            "category": "Database",
            "tasks": ["Database Management"],
            "domains": ["Software Developer", "Database Administrator"],
            "license": "Public Domain",
            "commercialUse": true,
            "description": "SQLite is a lightweight, embedded relational database engine, ideal for small applications and local data storage.",
            "link": "https://www.sqlite.org",
            "install": "sudo apt install sqlite3",
            "logo": "https://www.sqlite.org/images/sqlite370_banner.gif"
        },
        {
            "name": "MongoDB",
            "category": "Database",
            "tasks": ["Database Management", "Web Development"],
            "domains": ["Database Administrator", "Web Developer", "Software Developer"],
            "license": "SSPL-1.0",
            "commercialUse": true,
            "description": "MongoDB is a NoSQL database designed for scalability and flexibility, storing data in JSON-like documents.",
            "link": "https://www.mongodb.com",
            "install": "sudo apt install mongodb",
            "logo": "https://www.mongodb.com/assets/images/global/favicon.ico"
        },
        {
            "name": "Cassandra",
            "category": "Database",
            "tasks": ["Database Management", "Data Analysis"],
            "domains": ["Database Administrator", "Data Analyst"],
            "license": "Apache-2.0",
            "commercialUse": true,
            "description": "Apache Cassandra is a distributed NoSQL database designed for high availability and handling large datasets.",
            "link": "https://cassandra.apache.org",
            "install": "sudo apt install cassandra",
            "logo": "https://cassandra.apache.org/_/img/logo.png"
        },
        {
            "name": "Redis",
            "category": "Database",
            "tasks": ["Database Management", "Web Development"],
            "domains": ["Database Administrator", "Web Developer", "Software Developer"],
            "license": "BSD-3-Clause",
            "commercialUse": true,
            "description": "Redis is an in-memory data structure store used as a database, cache, and message broker, known for its speed.",
            "link": "https://redis.io",
            "install": "sudo apt install redis",
            "logo": "https://redis.io/images/redis-white.png"
        },
        {
            "name": "Elasticsearch",
            "category": "Search Engine",
            "tasks": ["Database Management", "Data Analysis"],
            "domains": ["Database Administrator", "Data Analyst", "Web Developer"],
            "license": "Apache-2.0",
            "commercialUse": true,
            "description": "Elasticsearch is a distributed search and analytics engine, ideal for indexing and querying large datasets.",
            "link": "https://www.elastic.co",
            "install": "sudo apt install elasticsearch",
            "logo": "https://www.elastic.co/assets/bltada7771f270d08f6/elastic-logo.svg"
        },
        {
            "name": "Apache HBase",
            "category": "Database",
            "tasks": ["Database Management", "Data Analysis"],
            "domains": ["Database Administrator", "Data Analyst"],
            "license": "Apache-2.0",
            "commercialUse": true,
            "description": "Apache HBase is a distributed, scalable NoSQL database built on Hadoop HDFS, suited for real-time read/write access.",
            "link": "https://hbase.apache.org",
            "install": "sudo apt install hbase",
            "logo": "https://hbase.apache.org/images/hbase_logo.png"
        },
        {
            "name": "CouchDB",
            "category": "Database",
            "tasks": ["Database Management", "Web Development"],
            "domains": ["Database Administrator", "Web Developer"],
            "license": "Apache-2.0",
            "commercialUse": true,
            "description": "CouchDB is a NoSQL database with a focus on ease of use and replication, storing data in JSON documents.",
            "link": "https://couchdb.apache.org",
            "install": "sudo apt install couchdb",
            "logo": "https://couchdb.apache.org/image/couchdb-logo.png"
        },
        {
            "name": "ArangoDB",
            "category": "Database",
            "tasks": ["Database Management", "Data Analysis"],
            "domains": ["Database Administrator", "Data Analyst", "Software Developer"],
            "license": "Apache-2.0",
            "commercialUse": true,
            "description": "ArangoDB is a multi-model NoSQL database supporting key-value, document, and graph data models.",
            "link": "https://www.arangodb.com",
            "install": "sudo apt install arangodb3",
            "logo": "https://www.arangodb.com/wp-content/uploads/2016/03/ArangoDB_logo.png"
        },
        {
            "name": "Neo4j",
            "category": "Database",
            "tasks": ["Database Management", "Data Analysis"],
            "domains": ["Database Administrator", "Data Analyst", "Software Developer"],
            "license": "GPL-3.0",
            "commercialUse": true,
            "description": "Neo4j is a graph database designed for managing relationships and networks, popular in data analysis and AI.",
            "link": "https://neo4j.com",
            "install": "sudo apt install neo4j",
            "logo": "https://neo4j.com/wp-content/themes/neo4jweb/assets/images/neo4j-logo-2015.png"
        },
        {
            "name": "Apache HTTP Server",
            "category": "Web Server",
            "tasks": ["Web Development", "File Sharing", "Network Monitoring"],
            "domains": ["Web Developer", "System Administrator", "Marketing Specialist"],
            "license": "Apache-2.0",
            "commercialUse": true,
            "description": "Apache HTTP Server is a robust, widely-used web server software powering a significant portion of the internet with its modular architecture.",
            "link": "https://httpd.apache.org",
            "install": "sudo apt install apache2",
            "logo": "https://httpd.apache.org/images/apache_pb.png"
        },
        {
            "name": "Nginx",
            "category": "Web Server",
            "tasks": ["Web Development", "File Sharing", "Network Monitoring"],
            "domains": ["Web Developer", "System Administrator"],
            "license": "BSD-2-Clause",
            "commercialUse": true,
            "description": "Nginx is a high-performance web server and reverse proxy known for its efficiency, scalability, and low resource usage.",
            "link": "https://nginx.org",
            "install": "sudo apt install nginx",
            "logo": "https://nginx.org/nginx.png"
        },
        {
            "name": "Lighttpd",
            "category": "Web Server",
            "tasks": ["Web Development", "File Sharing"],
            "domains": ["Web Developer", "System Administrator"],
            "license": "BSD-3-Clause",
            "commercialUse": true,
            "description": "Lighttpd is a lightweight web server optimized for speed and low resource usage, suitable for high-performance environments.",
            "link": "https://www.lighttpd.net",
            "install": "sudo apt install lighttpd",
            "logo": "https://www.lighttpd.net/assets/logo.png"
        },
        {
            "name": "Tomcat",
            "category": "Application Server",
            "tasks": ["Web Development"],
            "domains": ["Web Developer", "Software Developer"],
            "license": "Apache-2.0",
            "commercialUse": true,
            "description": "Apache Tomcat is an open-source Java servlet container, widely used for running Java-based web applications.",
            "link": "https://tomcat.apache.org",
            "install": "sudo apt install tomcat9",
            "logo": "https://tomcat.apache.org/res/images/tomcat.png"
        },
        {
            "name": "Node.js",
            "category": "Runtime Environment",
            "tasks": ["Web Development", "Code Writing"],
            "domains": ["Web Developer", "Software Developer"],
            "license": "MIT",
            "commercialUse": true,
            "description": "Node.js is a JavaScript runtime built on Chrome's V8 engine, enabling server-side development with an event-driven architecture.",
            "link": "https://nodejs.org",
            "install": "sudo apt install nodejs",
            "logo": "https://nodejs.org/static/images/logo.svg"
        },
        {
            "name": "Django",
            "category": "Web Framework",
            "tasks": ["Web Development", "Code Writing"],
            "domains": ["Web Developer", "Software Developer"],
            "license": "BSD-3-Clause",
            "commercialUse": true,
            "description": "Django is a high-level Python web framework that encourages rapid development and clean, pragmatic design.",
            "link": "https://www.djangoproject.com",
            "install": "pip install django",
            "logo": "https://www.djangoproject.com/m/img/logos/django-logo-positive.png"
        },
        {
            "name": "Ruby on Rails",
            "category": "Web Framework",
            "tasks": ["Web Development", "Code Writing"],
            "domains": ["Web Developer", "Software Developer"],
            "license": "MIT",
            "commercialUse": true,
            "description": "Ruby on Rails is a Ruby-based web framework focused on developer happiness and productivity with convention over configuration.",
            "link": "https://rubyonrails.org",
            "install": "gem install rails",
            "logo": "https://rubyonrails.org/images/rails-logo.svg"
        },
        {
            "name": "Spring Framework",
            "category": "Web Framework",
            "tasks": ["Web Development", "Code Writing"],
            "domains": ["Web Developer", "Software Developer"],
            "license": "Apache-2.0",
            "commercialUse": true,
            "description": "Spring Framework is a Java framework for building robust enterprise applications, with extensive support for web development.",
            "link": "https://spring.io",
            "install": "Available via Maven/Gradle",
            "logo": "https://spring.io/img/spring-by-pivotal.png"
        },
        {
            "name": "Laravel",
            "category": "Web Framework",
            "tasks": ["Web Development", "Code Writing"],
            "domains": ["Web Developer", "Software Developer"],
            "license": "MIT",
            "commercialUse": true,
            "description": "Laravel is a PHP framework with an elegant syntax, designed for web artisans to build modern applications.",
            "link": "https://laravel.com",
            "install": "composer create-project laravel/laravel",
            "logo": "https://laravel.com/img/logomark.min.svg"
        },
        {
            "name": "Flask",
            "category": "Web Framework",
            "tasks": ["Web Development", "Code Writing"],
            "domains": ["Web Developer", "Software Developer"],
            "license": "BSD-3-Clause",
            "commercialUse": true,
            "description": "Flask is a lightweight Python web framework, ideal for small to medium applications with a simple and flexible design.",
            "link": "https://flask.palletsprojects.com",
            "install": "pip install flask",
            "logo": "https://flask.palletsprojects.com/en/2.0.x/_static/flask-icon.png"
        },
        {
            "name": "Express.js",
            "category": "Web Framework",
            "tasks": ["Web Development", "Code Writing"],
            "domains": ["Web Developer", "Software Developer"],
            "license": "MIT",
            "commercialUse": true,
            "description": "Express.js is a minimal and flexible Node.js web application framework, providing robust features for web and mobile apps.",
            "link": "https://expressjs.com",
            "install": "npm install express",
            "logo": "https://expressjs.com/images/favicon.png"
        },
        {
            "name": "FastAPI",
            "category": "Web Framework",
            "tasks": ["Web Development", "Code Writing"],
            "domains": ["Web Developer", "Software Developer"],
            "license": "MIT",
            "commercialUse": true,
            "description": "FastAPI is a modern, fast Python web framework for building APIs with automatic data validation and high performance.",
            "link": "https://fastapi.tiangolo.com",
            "install": "pip install fastapi",
            "logo": "https://fastapi.tiangolo.com/img/favicon.png"
        },
        {
            "name": "Tornado",
            "category": "Web Framework",
            "tasks": ["Web Development", "Code Writing"],
            "domains": ["Web Developer", "Software Developer"],
            "license": "Apache-2.0",
            "commercialUse": true,
            "description": "Tornado is a Python web framework and asynchronous networking library, designed for handling thousands of simultaneous connections.",
            "link": "https://www.tornadoweb.org",
            "install": "pip install tornado",
            "logo": "https://www.tornadoweb.org/en/stable/_static/tornado.png"
        },
        {
            "name": "Caddy",
            "category": "Web Server",
            "tasks": ["Web Development", "File Sharing"],
            "domains": ["Web Developer", "System Administrator"],
            "license": "Apache-2.0",
            "commercialUse": true,
            "description": "Caddy is a modern web server with automatic HTTPS by default, designed for simplicity and security.",
            "link": "https://caddyserver.com",
            "install": "sudo apt install caddy",
            "logo": "https://caddyserver.com/resources/images/caddy-logo.svg"
        },
        {
            "name": "Git",
            "category": "Version Control",
            "tasks": ["Version Control", "Code Writing"],
            "domains": ["Software Developer", "Web Developer", "Technical Writer", "Game Developer"],
            "license": "GPL-2.0",
            "commercialUse": true,
            "description": "Git is a distributed version control system for tracking code changes, enabling seamless collaboration across development teams.",
            "link": "https://git-scm.com",
            "install": "sudo apt install git",
            "logo": "https://git-scm.com/images/logos/logomark-orange@2x.png"
        },
        {
            "name": "Subversion (SVN)",
            "category": "Version Control",
            "tasks": ["Version Control"],
            "domains": ["Software Developer", "Web Developer"],
            "license": "Apache-2.0",
            "commercialUse": true,
            "description": "Subversion (SVN) is a centralized version control system, widely used for managing code repositories before Git's rise.",
            "link": "https://subversion.apache.org",
            "install": "sudo apt install subversion",
            "logo": "https://subversion.apache.org/logos/subversion-logo.png"
        },
        {
            "name": "Mercurial",
            "category": "Version Control",
            "tasks": ["Version Control"],
            "domains": ["Software Developer", "Web Developer"],
            "license": "GPL-2.0",
            "commercialUse": true,
            "description": "Mercurial is a distributed version control system known for its simplicity and performance, an alternative to Git.",
            "link": "https://www.mercurial-scm.org",
            "install": "sudo apt install mercurial",
            "logo": "https://www.mercurial-scm.org/images/mercurial-logo.png"
        },
        {
            "name": "GitLab",
            "category": "DevOps Platform",
            "tasks": ["Version Control", "Web Development"],
            "domains": ["Software Developer", "Web Developer", "DevOps Engineer"],
            "license": "MIT",
            "commercialUse": true,
            "description": "GitLab is a web-based DevOps lifecycle tool with Git repository management, CI/CD, and collaboration features.",
            "link": "https://about.gitlab.com",
            "install": "sudo apt install gitlab-ce",
            "logo": "https://about.gitlab.com/images/press/logo/png/gitlab-logo-200.png"
        },
        {
            "name": "Bitbucket",
            "category": "Code Hosting",
            "tasks": ["Version Control"],
            "domains": ["Software Developer", "Web Developer"],
            "license": "Proprietary (Open-Source Tools)",
            "commercialUse": true,
            "description": "Bitbucket provides Git and Mercurial repository hosting with collaboration tools, integrated with Atlassian products.",
            "link": "https://bitbucket.org",
            "install": "Client tools via pip/npm",
            "logo": "https://bitbucket.org/favicon.ico"
        },
        {
            "name": "SourceForge",
            "category": "Project Hosting",
            "tasks": ["Version Control"],
            "domains": ["Software Developer"],
            "license": "Various",
            "commercialUse": true,
            "description": "SourceForge is a platform for hosting open-source projects, offering Git, SVN, and Mercurial repository management.",
            "link": "https://sourceforge.net",
            "install": "Web-based",
            "logo": "https://sourceforge.net/images/sf-icon.png"
        },
        {
            "name": "GitHub",
            "category": "Collaboration Platform",
            "tasks": ["Version Control", "Code Writing"],
            "domains": ["Software Developer", "Web Developer", "Technical Writer"],
            "license": "MIT (Client Tools)",
            "commercialUse": true,
            "description": "GitHub is a leading platform for Git-based collaboration, offering repository hosting, CI/CD, and community features.",
            "link": "https://github.com",
            "install": "gh CLI: sudo apt install gh",
            "logo": "https://github.githubassets.com/images/modules/logos_page/GitHub-Mark.png"
        },
        {
            "name": "Phabricator",
            "category": "Development Tools",
            "tasks": ["Version Control", "Code Writing"],
            "domains": ["Software Developer", "Web Developer"],
            "license": "Apache-2.0",
            "commercialUse": true,
            "description": "Phabricator is a suite of tools for software development, including code review, repository hosting, and project management.",
            "link": "https://www.phacility.com/phabricator/",
            "install": "Manual setup via website",
            "logo": "https://www.phacility.com/images/phabricator.png"
        },
        {
            "name": "GitBucket",
            "category": "Git Platform",
            "tasks": ["Version Control"],
            "domains": ["Software Developer", "Web Developer"],
            "license": "Apache-2.0",
            "commercialUse": true,
            "description": "GitBucket is a self-hosted Git platform with GitHub-like features, including issue tracking and pull requests.",
            "link": "https://gitbucket.github.io",
            "install": "Download JAR from website",
            "logo": "https://gitbucket.github.io/gitbucket-news/images/gitbucket.png"
        },
        {
            "name": "Redmine",
            "category": "Project Management",
            "tasks": ["Version Control", "Presentation Creation"],
            "domains": ["Product Manager", "Software Developer", "Event Planner"],
            "license": "GPL-2.0",
            "commercialUse": true,
            "description": "Redmine is a flexible project management tool with issue tracking, Gantt charts, and wiki features for team collaboration.",
            "link": "https://www.redmine.org",
            "install": "sudo apt install redmine",
            "logo": "https://www.redmine.org/attachments/download/117/redmine-logo.png"
        },
        {
            "name": "Taiga",
            "category": "Project Management",
            "tasks": ["Presentation Creation"],
            "domains": ["Product Manager", "Event Planner"],
            "license": "AGPL-3.0",
            "commercialUse": true,
            "description": "Taiga is an open-source Agile project management tool, designed for simplicity and team collaboration.",
            "link": "https://taiga.io",
            "install": "Docker or manual setup",
            "logo": "https://taiga.io/images/taiga-logo.png"
        },
        {
            "name": "OpenProject",
            "category": "Project Management",
            "tasks": ["Presentation Creation", "Version Control"],
            "domains": ["Product Manager", "Software Developer", "Event Planner"],
            "license": "GPL-3.0",
            "commercialUse": true,
            "description": "OpenProject is a collaborative project management tool with features for planning, tracking, and team coordination.",
            "link": "https://www.openproject.org",
            "install": "sudo apt install openproject",
            "logo": "https://www.openproject.org/assets/favicon.ico"
        },
        {
            "name": "Kanboard",
            "category": "Project Management",
            "tasks": ["Presentation Creation"],
            "domains": ["Product Manager", "Event Planner"],
            "license": "MIT",
            "commercialUse": true,
            "description": "Kanboard is a lightweight, open-source kanban board tool for managing tasks and projects efficiently.",
            "link": "https://kanboard.org",
            "install": "Manual setup via website",
            "logo": "https://kanboard.org/assets/img/logo.png"
        },
        {
            "name": "Wekan",
            "category": "Project Management",
            "tasks": ["Presentation Creation"],
            "domains": ["Product Manager", "Event Planner"],
            "license": "MIT",
            "commercialUse": true,
            "description": "Wekan is an open-source kanban board platform, offering Trello-like functionality for task management.",
            "link": "https://wekan.github.io",
            "install": "sudo snap install wekan",
            "logo": "https://wekan.github.io/wekan-logo.png"
        },
        {
            "name": "Restyaboard",
            "category": "Project Management",
            "tasks": ["Presentation Creation"],
            "domains": ["Product Manager", "Event Planner"],
            "license": "OSL-3.0",
            "commercialUse": true,
            "description": "Restyaboard is an open-source alternative to Trello, providing kanban-style task management and collaboration.",
            "link": "https://restya.com/board",
            "install": "Docker or manual setup",
            "logo": "https://restya.com/img/restyaboard_logo.png"
        },
        {
            "name": "Mattermost",
            "category": "Team Chat",
            "tasks": ["File Sharing"],
            "domains": ["Software Developer", "Administrative Assistant", "Event Planner"],
            "license": "MIT",
            "commercialUse": true,
            "description": "Mattermost is an open-source team communication platform, offering Slack-like features with self-hosting options.",
            "link": "https://mattermost.com",
            "install": "sudo snap install mattermost-server",
            "logo": "https://mattermost.com/wp-content/uploads/2022/02/MM_logo_horizontal.png"
        },
        {
            "name": "Rocket.Chat",
            "category": "Team Chat",
            "tasks": ["File Sharing"],
            "domains": ["Software Developer", "Administrative Assistant", "Event Planner"],
            "license": "MIT",
            "commercialUse": true,
            "description": "Rocket.Chat is an open-source chat platform for team communication, with support for video calls and integrations.",
            "link": "https://rocket.chat",
            "install": "sudo snap install rocketchat-server",
            "logo": "https://rocket.chat/images/logo/logo.svg"
        },
        {
            "name": "Zulip",
            "category": "Team Chat",
            "tasks": ["File Sharing"],
            "domains": ["Software Developer", "Administrative Assistant", "Event Planner"],
            "license": "Apache-2.0",
            "commercialUse": true,
            "description": "Zulip is an open-source chat platform with threaded conversations, designed for productivity and team collaboration.",
            "link": "https://zulip.com",
            "install": "Docker or manual setup",
            "logo": "https://zulip.com/static/images/logo/zulip-icon-circle.svg"
        },
        {
            "name": "Nextcloud",
            "category": "Cloud Storage",
            "tasks": ["File Sharing", "Document Editing", "Presentation Creation"],
            "domains": ["Administrative Assistant", "Teacher", "Marketing Specialist", "Writer"],
            "license": "AGPL-3.0",
            "commercialUse": true,
            "description": "Nextcloud is a self-hosted cloud platform for file sharing, collaboration, and productivity, offering secure data management.",
            "link": "https://nextcloud.com",
            "install": "sudo snap install nextcloud",
            "logo": "https://nextcloud.com/wp-content/themes/next/assets/img/common/favicon.png"
        },
        {
            "name": "OwnCloud",
            "category": "Cloud Storage",
            "tasks": ["File Sharing", "Document Editing"],
            "domains": ["Administrative Assistant", "Teacher", "Marketing Specialist"],
            "license": "AGPL-3.0",
            "commercialUse": true,
            "description": "OwnCloud is an open-source file sync and share platform, providing secure cloud storage and collaboration tools.",
            "link": "https://owncloud.com",
            "install": "Manual setup via website",
            "logo": "https://owncloud.com/wp-content/uploads/2020/03/owncloud-logo.png"
        },
        {
            "name": "Discourse",
            "category": "Forum Software",
            "tasks": ["File Sharing"],
            "domains": ["Web Content Manager", "Teacher"],
            "license": "GPL-2.0",
            "commercialUse": true,
            "description": "Discourse is a modern, open-source forum platform designed for community discussions and collaboration.",
            "link": "https://www.discourse.org",
            "install": "Docker or manual setup",
            "logo": "https://www.discourse.org/favicon.ico"
        },
        {
            "name": "Focalboard",
            "category": "Project Management",
            "tasks": ["Presentation Creation"],
            "domains": ["Product Manager", "Event Planner"],
            "license": "MIT",
            "commercialUse": true,
            "description": "Focalboard is an open-source project management tool with kanban boards, integrated with Mattermost.",
            "link": "https://www.focalboard.com",
            "install": "Docker or manual setup",
            "logo": "https://www.focalboard.com/favicon.ico"
        },
        {
            "name": "Moodle",
            "category": "Learning Management",
            "tasks": ["Presentation Creation", "File Sharing"],
            "domains": ["Teacher", "Education Specialist"],
            "license": "GPL-3.0",
            "commercialUse": true,
            "description": "Moodle is an open-source learning management system for creating online courses and educational content.",
            "link": "https://moodle.org",
            "install": "sudo apt install moodle",
            "logo": "https://moodle.org/theme/image.php/boost/core/1600425600/moodle_logo"
        },
        {
            "name": "Wiki.js",
            "category": "Wiki Software",
            "tasks": ["Document Editing"],
            "domains": ["Technical Writer", "Teacher"],
            "license": "AGPL-3.0",
            "commercialUse": true,
            "description": "Wiki.js is a modern, lightweight wiki platform with Markdown support and a clean interface.",
            "link": "https://js.wiki",
            "install": "Docker or manual setup",
            "logo": "https://js.wiki/images/logo.png"
        },
        {
            "name": "Docker",
            "category": "Containerization",
            "tasks": ["Web Development", "Network Monitoring", "Code Writing"],
            "domains": ["Software Developer", "System Administrator", "DevOps Engineer"],
            "license": "Apache-2.0",
            "commercialUse": true,
            "description": "Docker packages applications into containers, ensuring consistency across development and production environments.",
            "link": "https://www.docker.com",
            "install": "sudo apt install docker.io",
            "logo": "https://www.docker.com/wp-content/uploads/2023/04/Docker-Logo-Color.png"
        },
        {
            "name": "Kubernetes",
            "category": "Container Orchestration",
            "tasks": ["Network Monitoring", "Web Development"],
            "domains": ["Software Developer", "System Administrator", "DevOps Engineer"],
            "license": "Apache-2.0",
            "commercialUse": true,
            "description": "Kubernetes automates deployment, scaling, and management of containerized applications, a cornerstone of cloud-native development.",
            "link": "https://kubernetes.io",
            "install": "sudo snap install kubectl --classic",
            "logo": "https://kubernetes.io/images/favicon.png"
        },
        {
            "name": "Vagrant",
            "category": "Virtualization",
            "tasks": ["Web Development", "Code Writing"],
            "domains": ["Software Developer", "DevOps Engineer"],
            "license": "MIT",
            "commercialUse": true,
            "description": "Vagrant simplifies the creation and management of virtual development environments with a consistent workflow.",
            "link": "https://www.vagrantup.com",
            "install": "sudo apt install vagrant",
            "logo": "https://www.vagrantup.com/assets/images/logo-vagrant.png"
        },
        {
            "name": "VirtualBox",
            "category": "Virtualization",
            "tasks": ["Network Monitoring", "Code Writing"],
            "domains": ["Software Developer", "System Administrator"],
            "license": "GPL-2.0",
            "commercialUse": true,
            "description": "VirtualBox is a powerful virtualization tool for running multiple operating systems on a single machine.",
            "link": "https://www.virtualbox.org",
            "install": "sudo apt install virtualbox",
            "logo": "https://www.virtualbox.org/graphics/vbox_logo2_gradient.png"
        },
        {
            "name": "QEMU",
            "category": "Virtualization",
            "tasks": ["Network Monitoring"],
            "domains": ["System Administrator", "Software Developer"],
            "license": "GPL-2.0",
            "commercialUse": true,
            "description": "QEMU is an open-source emulator and virtualizer, supporting a wide range of architectures and operating systems.",
            "link": "https://www.qemu.org",
            "install": "sudo apt install qemu",
            "logo": "https://www.qemu.org/images/qemu-logo.png"
        },
        {
            "name": "LXC",
            "category": "Containerization",
            "tasks": ["Network Monitoring"],
            "domains": ["System Administrator", "DevOps Engineer"],
            "license": "LGPL-2.1",
            "commercialUse": true,
            "description": "LXC provides lightweight Linux containers, offering an alternative to Docker with OS-level virtualization.",
            "link": "https://linuxcontainers.org",
            "install": "sudo apt install lxc",
            "logo": "https://linuxcontainers.org/static/img/logo.png"
        },
        {
            "name": "Proxmox",
            "category": "Virtualization",
            "tasks": ["Network Monitoring"],
            "domains": ["System Administrator", "DevOps Engineer"],
            "license": "AGPL-3.0",
            "commercialUse": true,
            "description": "Proxmox is an open-source platform for virtualization and container management, with a web-based interface.",
            "link": "https://www.proxmox.com",
            "install": "Manual ISO install",
            "logo": "https://www.proxmox.com/images/proxmox/proxmox-logo.png"
        },
        {
            "name": "KVM",
            "category": "Virtualization",
            "tasks": ["Network Monitoring"],
            "domains": ["System Administrator", "DevOps Engineer"],
            "license": "GPL-2.0",
            "commercialUse": true,
            "description": "KVM (Kernel-based Virtual Machine) is a virtualization solution built into the Linux kernel, offering high performance.",
            "link": "https://www.linux-kvm.org",
            "install": "sudo apt install qemu-kvm",
            "logo": "https://www.linux-kvm.org/images/kvm-logo.png"
        },
        {
            "name": "Minikube",
            "category": "Container Orchestration",
            "tasks": ["Network Monitoring"],
            "domains": ["DevOps Engineer", "Software Developer"],
            "license": "Apache-2.0",
            "commercialUse": true,
            "description": "Minikube is a tool for running Kubernetes locally, ideal for learning and development purposes.",
            "link": "https://minikube.sigs.k8s.io",
            "install": "sudo snap install minikube",
            "logo": "https://minikube.sigs.k8s.io/images/logo.png"
        },
        {
            "name": "Podman",
            "category": "Containerization",
            "tasks": ["Web Development", "Network Monitoring"],
            "domains": ["DevOps Engineer", "Software Developer"],
            "license": "Apache-2.0",
            "commercialUse": true,
            "description": "Podman is a daemonless container engine, providing a Docker-compatible alternative with enhanced security.",
            "link": "https://podman.io",
            "install": "sudo apt install podman",
            "logo": "https://podman.io/images/podman.svg"
        },
        {
            "name": "Rancher",
            "category": "Container Management",
            "tasks": ["Network Monitoring"],
            "domains": ["DevOps Engineer", "System Administrator"],
            "license": "Apache-2.0",
            "commercialUse": true,
            "description": "Rancher is an open-source platform for managing Kubernetes clusters across multiple environments.",
            "link": "https://rancher.com",
            "install": "Docker or manual setup",
            "logo": "https://rancher.com/assets/img/rancher-logo-horiz.png"
        },
        {
            "name": "OpenStack",
            "category": "Cloud Infrastructure",
            "tasks": ["Network Monitoring"],
            "domains": ["System Administrator", "DevOps Engineer"],
            "license": "Apache-2.0",
            "commercialUse": true,
            "description": "OpenStack is an open-source cloud computing platform for building and managing private and public clouds.",
            "link": "https://www.openstack.org",
            "install": "Manual setup via website",
            "logo": "https://www.openstack.org/themes/openstack/images/openstack-logo-full.png"
        },
        {
            "name": "Wireshark",
            "category": "Network Analyzer",
            "tasks": ["Network Monitoring"],
            "domains": ["System Administrator", "Engineer", "Software Developer"],
            "license": "GPL-2.0",
            "commercialUse": true,
            "description": "Wireshark is a network protocol analyzer for capturing and analyzing traffic, widely used for troubleshooting and security.",
            "link": "https://www.wireshark.org",
            "install": "sudo apt install wireshark",
            "logo": "https://www.wireshark.org/assets/images/wireshark_logo.png"
        },
        {
            "name": "Nmap",
            "category": "Network Scanner",
            "tasks": ["Network Monitoring"],
            "domains": ["System Administrator", "Engineer"],
            "license": "GPL-2.0",
            "commercialUse": true,
            "description": "Nmap is a network scanning tool for discovering hosts and services, widely used in security auditing.",
            "link": "https://nmap.org",
            "install": "sudo apt install nmap",
            "logo": "https://nmap.org/images/nmap-logo.png"
        },
        {
            "name": "OpenVPN",
            "category": "VPN",
            "tasks": ["Network Monitoring"],
            "domains": ["System Administrator", "Software Developer"],
            "license": "GPL-2.0",
            "commercialUse": true,
            "description": "OpenVPN is an open-source VPN solution for secure point-to-point and site-to-site connections.",
            "link": "https://openvpn.net",
            "install": "sudo apt install openvpn",
            "logo": "https://openvpn.net/wp-content/uploads/openvpn-logo.png"
        },
        {
            "name": "WireGuard",
            "category": "VPN",
            "tasks": ["Network Monitoring"],
            "domains": ["System Administrator", "Software Developer"],
            "license": "GPL-2.0",
            "commercialUse": true,
            "description": "WireGuard is a modern, high-performance VPN protocol with a simple and secure design.",
            "link": "https://www.wireguard.com",
            "install": "sudo apt install wireguard",
            "logo": "https://www.wireguard.com/img/wireguard.svg"
        },
        {
            "name": "Suricata",
            "category": "Intrusion Detection",
            "tasks": ["Network Monitoring"],
            "domains": ["System Administrator"],
            "license": "GPL-2.0",
            "commercialUse": true,
            "description": "Suricata is an open-source intrusion detection and prevention system, offering real-time network security monitoring.",
            "link": "https://suricata-ids.org",
            "install": "sudo apt install suricata",
            "logo": "https://suricata-ids.org/images/suricata-logo.png"
        },
        {
            "name": "Snort",
            "category": "Intrusion Detection",
            "tasks": ["Network Monitoring"],
            "domains": ["System Administrator"],
            "license": "GPL-2.0",
            "commercialUse": true,
            "description": "Snort is an open-source network intrusion detection system, capable of real-time traffic analysis and packet logging.",
            "link": "https://www.snort.org",
            "install": "sudo apt install snort",
            "logo": "https://www.snort.org/images/snort_logo.png"
        },
        {
            "name": "Metasploit Framework",
            "category": "Penetration Testing",
            "tasks": ["Network Monitoring"],
            "domains": ["System Administrator", "Engineer"],
            "license": "BSD-3-Clause",
            "commercialUse": true,
            "description": "Metasploit Framework is an open-source penetration testing tool for security researchers and professionals.",
            "link": "https://www.metasploit.com",
            "install": "sudo apt install metasploit-framework",
            "logo": "https://www.metasploit.com/images/metasploit-logo.png"
        },
        {
            "name": "OWASP ZAP",
            "category": "Security Tool",
            "tasks": ["Network Monitoring"],
            "domains": ["System Administrator", "Web Developer"],
            "license": "Apache-2.0",
            "commercialUse": true,
            "description": "OWASP ZAP is an open-source web application security scanner, ideal for finding vulnerabilities in web apps.",
            "link": "https://www.zaproxy.org",
            "install": "sudo apt install zaproxy",
            "logo": "https://www.zaproxy.org/images/zap-logo.png"
        },
        {
            "name": "Fail2ban",
            "category": "Security Tool",
            "tasks": ["Network Monitoring"],
            "domains": ["System Administrator"],
            "license": "GPL-2.0",
            "commercialUse": true,
            "description": "Fail2ban protects servers from brute-force attacks by banning IPs after repeated failed login attempts.",
            "link": "https://www.fail2ban.org",
            "install": "sudo apt install fail2ban",
            "logo": "https://www.fail2ban.org/images/fail2ban.png"
        },
        {
            "name": "Kali Linux",
            "category": "Security Distribution",
            "tasks": ["Network Monitoring"],
            "domains": ["System Administrator", "Engineer"],
            "license": "GPL-3.0",
            "commercialUse": true,
            "description": "Kali Linux is a specialized Linux distribution for security researchers and penetration testers, preloaded with tools.",
            "link": "https://www.kali.org",
            "install": "ISO install from website",
            "logo": "https://www.kali.org/images/kali-logo.png"
        },
        {
            "name": "Let's Encrypt",
            "category": "Certificate Authority",
            "tasks": ["Network Monitoring"],
            "domains": ["System Administrator", "Web Developer"],
            "license": "Apache-2.0",
            "commercialUse": true,
            "description": "Let's Encrypt is a free, automated certificate authority providing SSL/TLS certificates for secure websites.",
            "link": "https://letsencrypt.org",
            "install": "sudo apt install certbot",
            "logo": "https://letsencrypt.org/images/letsencrypt-logo-horizontal.png"
        },
        {
            "name": "LibreOffice",
            "category": "Office Suite",
            "tasks": ["Document Editing", "Presentation Creation", "Financial Tracking"],
            "domains": ["Administrative Assistant", "Teacher", "Accountant", "Writer"],
            "license": "MPL-2.0",
            "commercialUse": true,
            "description": "LibreOffice is a comprehensive office suite with tools for word processing, spreadsheets, and presentations, a free alternative to Microsoft Office.",
            "link": "https://www.libreoffice.org",
            "install": "sudo apt install libreoffice",
            "logo": "https://www.libreoffice.org/themes/libreoffice/images/logo.png"
        },
        {
            "name": "OnlyOffice",
            "category": "Office Suite",
            "tasks": ["Document Editing", "Presentation Creation", "Financial Tracking"],
            "domains": ["Administrative Assistant", "Teacher", "Accountant", "Writer"],
            "license": "AGPL-3.0",
            "commercialUse": true,
            "description": "OnlyOffice is an open-source office suite with collaborative tools for documents, spreadsheets, and presentations.",
            "link": "https://www.onlyoffice.com",
            "install": "sudo apt install onlyoffice-desktopeditors",
            "logo": "https://www.onlyoffice.com/assets/favicon.ico"
        },
        {
            "name": "Collabora Office",
            "category": "Office Suite",
            "tasks": ["Document Editing", "Presentation Creation"],
            "domains": ["Administrative Assistant", "Teacher", "Writer"],
            "license": "MPL-2.0",
            "commercialUse": true,
            "description": "Collabora Office is a LibreOffice-based suite optimized for collaboration and cloud integration.",
            "link": "https://www.collaboraoffice.com",
            "install": "sudo apt install collaboraoffice",
            "logo": "https://www.collaboraoffice.com/wp-content/uploads/2020/01/collabora-office-logo.png"
        },
        {
            "name": "Etherpad",
            "category": "Collaborative Editor",
            "tasks": ["Document Editing"],
            "domains": ["Writer", "Teacher"],
            "license": "Apache-2.0",
            "commercialUse": true,
            "description": "Etherpad is a real-time collaborative text editor, ideal for team writing and brainstorming sessions.",
            "link": "https://etherpad.org",
            "install": "Docker or manual setup",
            "logo": "https://etherpad.org/favicon.ico"
        },
        {
            "name": "Joplin",
            "category": "Note-Taking",
            "tasks": ["Document Editing"],
            "domains": ["Writer", "Teacher", "Administrative Assistant"],
            "license": "MIT",
            "commercialUse": true,
            "description": "Joplin is an open-source note-taking app with Markdown support and synchronization across devices.",
            "link": "https://joplinapp.org",
            "install": "sudo snap install joplin-desktop",
            "logo": "https://joplinapp.org/images/logo.png"
        },
        {
            "name": "Zotero",
            "category": "Reference Management",
            "tasks": ["Document Editing"],
            "domains": ["Research Scientist", "Writer", "Teacher"],
            "license": "AGPL-3.0",
            "commercialUse": true,
            "description": "Zotero is an open-source tool for managing bibliographic references and research materials.",
            "link": "https://www.zotero.org",
            "install": "sudo snap install zotero-snap",
            "logo": "https://www.zotero.org/static/images/theme/zotero-logo.png"
        },
        {
            "name": "Nextcloud Office",
            "category": "Online Office Suite",
            "tasks": ["Document Editing", "Presentation Creation"],
            "domains": ["Administrative Assistant", "Teacher", "Writer"],
            "license": "AGPL-3.0",
            "commercialUse": true,
            "description": "Nextcloud Office integrates collaborative office tools into the Nextcloud platform, powered by Collabora.",
            "link": "https://nextcloud.com/office/",
            "install": "Part of Nextcloud",
            "logo": "https://nextcloud.com/wp-content/themes/next/assets/img/common/favicon.png"
        },
        {
            "name": "Turtl",
            "category": "Note-Taking",
            "tasks": ["Document Editing"],
            "domains": ["Writer", "Teacher"],
            "license": "GPL-3.0",
            "commercialUse": true,
            "description": "Turtl is an open-source, secure note-taking app with encryption for private notes and collaboration.",
            "link": "https://turtlapp.com",
            "install": "Download from website",
            "logo": "https://turtlapp.com/images/turtl-logo.png"
        },
        {
            "name": "GIMP",
            "category": "Image Editor",
            "tasks": ["Photo Editing", "Desktop Publishing"],
            "domains": ["Graphic Designer", "Photographer", "Art Director", "Marketing Specialist"],
            "license": "GPL-3.0",
            "commercialUse": true,
            "description": "GIMP is a versatile image editing tool comparable to Photoshop, offering advanced features for photo retouching and graphic design.",
            "link": "https://www.gimp.org",
            "install": "sudo apt install gimp",
            "logo": "https://www.gimp.org/images/wilber32.png"
        },
        {
            "name": "Inkscape",
            "category": "Vector Graphics Editor",
            "tasks": ["Vectorize", "Create SVGs", "Desktop Publishing"],
            "domains": ["Graphic Designer", "Illustrator", "Architect", "Designer"],
            "license": "GPL-2.0",
            "commercialUse": true,
            "description": "Inkscape is a professional vector graphics editor for creating scalable designs like logos and illustrations, ideal for design and architecture.",
            "link": "https://inkscape.org",
            "install": "sudo apt install inkscape",
            "logo": "https://upload.wikimedia.org/wikipedia/commons/6/6e/Inkscape_logo.svg"
        },
        {
            "name": "Blender",
            "category": "3D Modeling Software",
            "tasks": ["3D Modeling", "Animation", "Video Editing", "Game Development"],
            "domains": ["Architect", "Graphic Designer", "Video Editor", "Game Developer", "Filmmaker"],
            "license": "GPL-2.0",
            "commercialUse": true,
            "description": "Blender is a comprehensive tool for 3D creation, offering modeling, animation, rendering, and more, used in film, gaming, and design.",
            "link": "https://www.blender.org",
            "install": "sudo apt install blender",
            "logo": "https://www.blender.org/wp-content/uploads/2019/07/blender_icon_32x32.png"
        },
        {
            "name": "Krita",
            "category": "Digital Painting",
            "tasks": ["Photo Editing", "Vectorize"],
            "domains": ["Graphic Designer", "Illustrator", "Designer"],
            "license": "GPL-3.0",
            "commercialUse": true,
            "description": "Krita is a professional digital painting tool, designed for artists with advanced brush engines and animation capabilities.",
            "link": "https://krita.org",
            "install": "sudo apt install krita",
            "logo": "https://krita.org/wp-content/uploads/2016/06/krita-logo.png"
        },
        {
            "name": "Darktable",
            "category": "Photo Editor",
            "tasks": ["Photo Editing"],
            "domains": ["Photographer", "Graphic Designer"],
            "license": "GPL-3.0",
            "commercialUse": true,
            "description": "Darktable is an open-source photography workflow application and raw developer, ideal for non-destructive editing.",
            "link": "https://www.darktable.org",
            "install": "sudo apt install darktable",
            "logo": "https://www.darktable.org/wp-content/uploads/2019/03/darktable-logo.png"
        },
        {
            "name": "RawTherapee",
            "category": "Photo Editor",
            "tasks": ["Photo Editing"],
            "domains": ["Photographer", "Graphic Designer"],
            "license": "GPL-3.0",
            "commercialUse": true,
            "description": "RawTherapee is an open-source raw image processing tool, offering advanced controls for photographers.",
            "link": "http://rawtherapee.com",
            "install": "sudo apt install rawtherapee",
            "logo": "http://rawtherapee.com/images/icon.png"
        },
        {
            "name": "Shotcut",
            "category": "Video Editor",
            "tasks": ["Video Editing"],
            "domains": ["Video Editor", "Filmmaker"],
            "license": "GPL-3.0",
            "commercialUse": true,
            "description": "Shotcut is a free, cross-platform video editor with support for a wide range of formats and effects.",
            "link": "https://shotcut.org",
            "install": "sudo snap install shotcut --classic",
            "logo": "https://shotcut.org/assets/img/shotcut-logo-64.png"
        },
        {
            "name": "OBS Studio",
            "category": "Streaming Software",
            "tasks": ["Video Editing", "Audio Recording"],
            "domains": ["Video Editor", "Filmmaker", "Teacher"],
            "license": "GPL-2.0",
            "commercialUse": true,
            "description": "OBS Studio is an open-source tool for video recording and live streaming, popular among content creators.",
            "link": "https://obsproject.com",
            "install": "sudo apt install obs-studio",
            "logo": "https://obsproject.com/assets/images/new_layout/obs_logo.png"
        },
        {
            "name": "Natron",
            "category": "Compositing Software",
            "tasks": ["Video Editing", "Animation"],
            "domains": ["Video Editor", "Filmmaker"],
            "license": "GPL-2.0",
            "commercialUse": true,
            "description": "Natron is an open-source compositing software for visual effects and motion graphics, similar to Nuke.",
            "link": "https://natrongithub.github.io",
            "install": "sudo snap install natron",
            "logo": "https://natrongithub.github.io/images/Natron_Icon.png"
        },
        {
            "name": "Scribus",
            "category": "Desktop Publishing",
            "tasks": ["Desktop Publishing"],
            "domains": ["Graphic Designer", "Marketing Specialist"],
            "license": "GPL-2.0",
            "commercialUse": true,
            "description": "Scribus is an open-source desktop publishing tool for creating professional layouts and print-ready documents.",
            "link": "https://www.scribus.net",
            "install": "sudo apt install scribus",
            "logo": "https://www.scribus.net/wp-content/uploads/2018/10/scribus-logo.png"
        },
        {
            "name": "Pencil2D",
            "category": "Animation",
            "tasks": ["Animation"],
            "domains": ["Graphic Designer", "Filmmaker"],
            "license": "GPL-2.0",
            "commercialUse": true,
            "description": "Pencil2D is a simple, open-source tool for creating 2D animations with raster and vector workflows.",
            "link": "https://www.pencil2d.org",
            "install": "sudo snap install pencil2d",
            "logo": "https://www.pencil2d.org/images/favicon.png"
        },
        {
            "name": "Synfig Studio",
            "category": "Animation",
            "tasks": ["Animation", "Vectorize"],
            "domains": ["Graphic Designer", "Filmmaker"],
            "license": "GPL-3.0",
            "commercialUse": true,
            "description": "Synfig Studio is an open-source 2D animation tool with vector-based animation capabilities.",
            "link": "https://www.synfig.org",
            "install": "sudo apt install synfigstudio",
            "logo": "https://www.synfig.org/wp-content/uploads/2018/03/synfig_icon.png"
        },
        {
            "name": "Audacity",
            "category": "Audio Editor",
            "tasks": ["Audio Recording", "Video Editing"],
            "domains": ["Video Editor", "Filmmaker", "Teacher", "Comedian", "Marketing Specialist"],
            "license": "GPL-2.0",
            "commercialUse": true,
            "description": "Audacity is a multi-track audio editor and recorder, excellent for podcasts, music production, and video soundtracks.",
            "link": "https://www.audacityteam.org",
            "install": "sudo apt install audacity",
            "logo": "https://www.audacityteam.org/wp-content/uploads/2019/02/audacity_logo.png"
        },
        {
            "name": "Ardour",
            "category": "Audio Workstation",
            "tasks": ["Audio Recording"],
            "domains": ["Video Editor", "Filmmaker"],
            "license": "GPL-2.0",
            "commercialUse": true,
            "description": "Ardour is a professional digital audio workstation for recording, editing, and mixing audio tracks.",
            "link": "https://ardour.org",
            "install": "sudo apt install ardour",
            "logo": "https://ardour.org/images/ardour-icon.png"
        },
        {
            "name": "LMMS",
            "category": "Music Production",
            "tasks": ["Audio Recording"],
            "domains": ["Filmmaker", "Comedian"],
            "license": "GPL-2.0",
            "commercialUse": true,
            "description": "LMMS is an open-source digital audio workstation for creating music with synthesizers, samples, and effects.",
            "link": "https://lmms.io",
            "install": "sudo apt install lmms",
            "logo": "https://lmms.io/img/lmms_logo.png"
        },
        {
            "name": "MuseScore",
            "category": "Music Notation",
            "tasks": ["Audio Recording"],
            "domains": ["Teacher", "Filmmaker"],
            "license": "GPL-2.0",
            "commercialUse": true,
            "description": "MuseScore is an open-source music notation software for composing and editing sheet music.",
            "link": "https://musescore.org",
            "install": "sudo apt install musescore",
            "logo": "https://musescore.org/sites/musescore.org/files/MuseScore_0.png"
        },
        {
            "name": "Clementine",
            "category": "Music Player",
            "tasks": ["Audio Recording"],
            "domains": ["Teacher", "Filmmaker"],
            "license": "GPL-3.0",
            "commercialUse": true,
            "description": "Clementine is a cross-platform music player with support for various audio formats and online streaming.",
            "link": "https://www.clementine-player.org",
            "install": "sudo apt install clementine",
            "logo": "https://www.clementine-player.org/images/clementine.png"
        },
        {
            "name": "VLC Media Player",
            "category": "Media Player",
            "tasks": ["Video Editing", "Audio Recording"],
            "domains": ["Video Editor", "Filmmaker", "Teacher"],
            "license": "GPL-2.0",
            "commercialUse": true,
            "description": "VLC is a versatile media player supporting nearly all audio and video formats, with features for playback and basic editing.",
            "link": "https://www.videolan.org/vlc/",
            "install": "sudo apt install vlc",
            "logo": "https://www.videolan.org/images/icon.png"
        },
        {
            "name": "HandBrake",
            "category": "Video Converter",
            "tasks": ["Video Editing"],
            "domains": ["Video Editor", "Filmmaker"],
            "license": "GPL-2.0",
            "commercialUse": true,
            "description": "HandBrake is an open-source video transcoder for converting video files into various formats.",
            "link": "https://handbrake.fr",
            "install": "sudo apt install handbrake",
            "logo": "https://handbrake.fr/img/logo.png"
        },
        {
            "name": "mpv",
            "category": "Media Player",
            "tasks": ["Video Editing"],
            "domains": ["Video Editor", "Filmmaker"],
            "license": "GPL-2.0",
            "commercialUse": true,
            "description": "mpv is a lightweight, highly configurable media player with support for a wide range of video and audio formats.",
            "link": "https://mpv.io",
            "install": "sudo apt install mpv",
            "logo": "https://mpv.io/favicon.ico"
        },
        {
            "name": "FFmpeg",
            "category": "Multimedia Tool",
            "tasks": ["Video Editing", "Audio Recording"],
            "domains": ["Video Editor", "Filmmaker"],
            "license": "LGPL-2.1",
            "commercialUse": true,
            "description": "FFmpeg is a powerful multimedia framework for handling video, audio, and other media files with extensive conversion options.",
            "link": "https://ffmpeg.org",
            "install": "sudo apt install ffmpeg",
            "logo": "https://ffmpeg.org/ffmpeg-logo.png"
        },
        {
            "name": "ownCloud",
            "category": "Cloud Storage",
            "tasks": ["File Sharing"],
            "domains": ["Administrative Assistant", "Teacher"],
            "license": "AGPL-3.0",
            "commercialUse": true,
            "description": "ownCloud is an open-source file sync and share platform, providing secure cloud storage and collaboration tools.",
            "link": "https://owncloud.com",
            "install": "Manual setup via website",
            "logo": "https://owncloud.com/wp-content/uploads/2020/03/owncloud-logo.png"
        },
        {
            "name": "Minio",
            "category": "Object Storage",
            "tasks": ["File Sharing"],
            "domains": ["System Administrator", "Software Developer"],
            "license": "AGPL-3.0",
            "commercialUse": true,
            "description": "Minio is an open-source object storage server compatible with Amazon S3, ideal for cloud-native applications.",
            "link": "https://min.io",
            "install": "Docker or manual setup",
            "logo": "https://min.io/resources/img/logo.png"
        },
        {
            "name": "Ceph",
            "category": "Distributed Storage",
            "tasks": ["File Sharing"],
            "domains": ["System Administrator"],
            "license": "LGPL-2.1",
            "commercialUse": true,
            "description": "Ceph is an open-source distributed storage system designed for scalability and reliability in cloud environments.",
            "link": "https://ceph.io",
            "install": "sudo apt install ceph",
            "logo": "https://ceph.io/wp-content/uploads/2018/08/ceph-logo.png"
        }],
    "domains": [
        "Accountant", "Administrative Assistant", "Architect", "Art Director", "Astronomer",
        "Biologist", "Cartographer", "Chemist", "Civil Engineer", "Comedian", "Copywriter",
        "Data Analyst", "Database Administrator", "Designer", "Economist", "Education Specialist",
        "Engineer", "Geographer", "Graphic Designer", "Historian", "Illustrator", "Inventor",
        "Journalist", "Landscape Architect", "Librarian", "Mathematician", "Meteorologist",
        "Photographer", "Product Manager", "Psychologist", "Research Scientist", "Robotics Engineer",
        "Salesperson", "Software Developer", "Teacher", "Technical Writer", "Translator",
        "UX Designer", "Video Editor", "Web Content Manager", "Writer", "Marketing Specialist",
        "Event Planner", "Nurse", "Lawyer", "Filmmaker", "Game Developer", "Web Developer",
        "Data Scientist", "System Administrator", "DevOps Engineer"
    ],
    "tasks": [
        "Code Writing", "Data Analysis", "Vectorize", "Create SVGs", "3D Modeling",
        "Document Editing", "File Sharing", "Map Creation", "Circuit Design", "Photo Editing",
        "Audio Recording", "Video Editing", "Game Development", "Network Monitoring",
        "Financial Tracking", "Presentation Creation", "Web Development", "Database Management",
        "Statistical Modeling", "Animation", "Version Control", "Browsing", "Desktop Publishing"
    ]
}